{
  "users": [
    {
      "email": "lucaskendy2002@gmail.com",
      "pass": "123123",
      "nome": "Lucas Kendy Urano",
      "idade": 21,
      "cargo": "Programador",
      "setor": "Desenvolvimento",
      "foto": "https://i.imgur.com/6LIfklc.jpg",
      "id": 1
    },
    {
      "email": "clima1528@gmail.com",
      "pass": "1273",
      "nome": "Clara Maria Lima",
      "idade": 20,
      "cargo": "Enfermeira",
      "setor": "Atendimento",
      "foto": "https://i.imgur.com/QK553sm.jpg",
      "id": 2
    },
    {
      "email": "daniele@email.com",
      "pass": "danidanidani",
      "nome": "Daniele Fabiana",
      "idade": 33,
      "cargo": "Atendente",
      "setor": "Atendimento",
      "id": 3
    },
    {
      "email": "pedro@email.com",
      "pass": "123123",
      "nome": "Pedro Barreiro",
      "idade": 20,
      "cargo": "Programador Web",
      "setor": "Desenvolvimento",
      "id": 4
    },
    {
      "email": "duda@email.com",
      "pass": "mariaeduarda123",
      "nome": "Maria Eduarda",
      "idade": 30,
      "cargo": "Arquiteta",
      "setor": "Projetos",
      "id": 5
    }
  ],
  "registros": []
}